{
  "title": "Best Jump Ropes for Fitness 2026",
  "slug": "best-jump-ropes-for-fitness-2026",
  "category": "Home Fitness",
  "date": "2026-05-08",
  "thumbnail": "https://m.media-amazon.com/images/I/71SSmkDjH+L._AC_SL1500_.jpg",
  "intro": "Jump ropes are one of the most effective and portable pieces of fitness equipment available — a 10-minute jump rope session burns more calories than a mile of jogging while also improving coordination, footwork, and cardiovascular capacity. They're used by boxers for conditioning, CrossFitters for double-unders, and casual exercisers looking for an intense, low-equipment workout anywhere.\n\nThe jump rope market has matured significantly, with products now engineered for specific use cases. Speed ropes designed for double-unders feature thin cables and precision ball bearings for ultra-fast rotation. Weighted ropes add resistance to upper body muscles during cardio. Smart ropes track reps electronically with LED displays. Heavy battle-style ropes serve as strength-conditioning tools. The handle design, cable material, and bearing quality determine whether a rope feels smooth and effortless or awkward and inconsistent.\n\nWe tested jump ropes across cardio conditioning sessions, HIIT workouts, and skill practice for double-unders, evaluating cable speed, handle comfort, bearing smoothness, adjustability, and durability. Whether you're a beginner looking for a basic cardio tool or an advanced athlete chasing sub-30-second double-under runs, here are the six best jump ropes for fitness in 2026.",
  "excerpt": "Jump ropes deliver high-intensity cardio anywhere with minimal gear. We tested the 6 best jump ropes for fitness, speed training, and double-unders in 2026.",
  "products": [
    {
      "name": "WOD Nation Speed Jump Rope",
      "price": "$19.95",
      "rating": "9.5/10",
      "best_for": "Best Overall",
      "image": "https://m.media-amazon.com/images/I/71SSmkDjH+L._AC_SL1500_.jpg",
      "link": "https://www.amazon.com/dp/B01ANCXS24?tag=compareelite-20",
      "pros": [
        "Precision ball-bearing handles for ultra-smooth rotation",
        "Includes two cables: 2.5mm thin-speed and 5mm weighted",
        "Adjustable length up to 10 feet for all heights",
        "Comfortable foam grip handles reduce fatigue",
        "Ideal for double-unders and CrossFit WODs"
      ],
      "cons": [
        "Thin cable can sting on missed reps",
        "Takes a few sessions to dial in length adjustment"
      ]
    },
    {
      "name": "Crossrope Get Lean Jump Rope Set",
      "price": "$78.00",
      "rating": "9.2/10",
      "best_for": "Best Weighted Set",
      "image": "https://m.media-amazon.com/images/I/71gJJLPqKxL._AC_SL1500_.jpg",
      "link": "https://www.amazon.com/dp/B07YN1SR63?tag=compareelite-20",
      "pros": [
        "Interchangeable 1/4 lb and 1/2 lb weighted ropes",
        "Quick-connect clips swap ropes in seconds",
        "App integration tracks workouts and guides programs",
        "Durable handles with ergonomic grip",
        "Weighted ropes intensify arms and shoulders"
      ],
      "cons": [
        "Premium price for the system",
        "Best value when you use the app ecosystem"
      ]
    },
    {
      "name": "Survival and Cross Speed Rope",
      "price": "$17.97",
      "rating": "9.0/10",
      "best_for": "Best Budget Speed Rope",
      "image": "https://m.media-amazon.com/images/I/71K1vGnCKZL._AC_SL1500_.jpg",
      "link": "https://www.amazon.com/dp/B00UL1DQIK?tag=compareelite-20",
      "pros": [
        "Thin 2mm speed cable for rapid rotation",
        "Ball-bearing handles for consistent spin",
        "Easily adjustable for heights 4'8\" to 6'8\"",
        "Comes with protective storage bag",
        "Great for beginners learning double-unders"
      ],
      "cons": [
        "Cable can kink if stored loosely",
        "Handles less ergonomic than premium options"
      ]
    },
    {
      "name": "Rogue SR-1 Speed Rope",
      "price": "$24.00",
      "rating": "8.8/10",
      "best_for": "Best for CrossFit Athletes",
      "image": "https://m.media-amazon.com/images/I/71ZJsTMRpIL._AC_SL1500_.jpg",
      "link": "https://www.amazon.com/dp/B00WXBGXHY?tag=compareelite-20",
      "pros": [
        "Precision-machined aluminum handles with ball bearings",
        "1.5mm steel cable rated for 150,000+ revolutions",
        "Available in multiple cable lengths without cutting",
        "Lightweight 90g total weight — barely notice it",
        "Trusted by competitive CrossFit athletes"
      ],
      "cons": [
        "Higher price than entry-level speed ropes",
        "Cable length must be specified at purchase"
      ]
    },
    {
      "name": "Buddy Lee Aero Speed Jump Rope",
      "price": "$44.95",
      "rating": "8.6/10",
      "best_for": "Best for Boxing Training",
      "image": "https://m.media-amazon.com/images/I/71B5TQJGZJL._AC_SL1500_.jpg",
      "link": "https://www.amazon.com/dp/B001VQUIIO?tag=compareelite-20",
      "pros": [
        "Designed by 3-time jump rope world champion",
        "Ultra-speed technology for rapid footwork training",
        "Swivel system prevents cable kinking",
        "Comfortable contoured handles with rubber grip",
        "Widely used in professional boxing programs"
      ],
      "cons": [
        "Premium price for a single rope",
        "Not ideal for total beginners — designed for athletes"
      ]
    },
    {
      "name": "DEGOL Skipping Rope with Counter",
      "price": "$14.99",
      "rating": "8.3/10",
      "best_for": "Best for Beginners",
      "image": "https://m.media-amazon.com/images/I/71oRqpJe5-L._AC_SL1500_.jpg",
      "link": "https://www.amazon.com/dp/B075TGYCJY?tag=compareelite-20",
      "pros": [
        "Built-in digital counter tracks jump count automatically",
        "Adjustable PVC rope fits all heights",
        "Memory foam handles for comfort during long sessions",
        "Calorie estimation display on handle",
        "Lightweight and portable — fits in any bag"
      ],
      "cons": [
        "PVC rope slower than steel cable speed ropes",
        "Counter battery not replaceable on all models"
      ]
    }
  ],
  "buying_guide": [
    {
      "title": "Speed Ropes vs. Weighted Ropes",
      "body": "Jump ropes divide into two primary categories based on purpose. Speed ropes feature thin steel or PVC cables (1.5-3mm diameter) and precision ball-bearing handles designed to rotate as fast as possible — ideal for double-unders, CrossFit conditioning, and footwork training. The thin cable creates minimal air resistance, allowing high rotation speeds with less effort. Weighted ropes add mass to the rope (1/4 lb to 2 lb total) to increase the workout intensity for arms, shoulders, and core — the heavier rope forces your muscles to work harder with each rotation. Weighted ropes are typically slower and not suitable for double-unders but provide a more intense upper-body conditioning effect. Some sets include both cable types with interchangeable handles, offering versatility between speed-focused and strength-focused sessions."
    },
    {
      "title": "Cable Material and Durability",
      "body": "Jump rope cables come in three primary materials: steel wire (fastest, most durable, stings on missed reps), PVC-coated steel (slightly slower but gentler on skin, more beginner-friendly), and pure PVC (slowest, most durable outdoors on rough surfaces, least suitable for speed training). Steel cables are standard for competitive and CrossFit use due to their speed, but they can leave welts when the cable misses a jump and hits bare legs — many athletes wear long socks when learning double-unders for this reason. PVC-coated options balance speed and comfort. For outdoor use on pavement or concrete, thicker PVC cables last much longer than thin steel cables. Choose cable material based on your training environment and tolerance for cable-miss contact."
    },
    {
      "title": "Sizing and Length Adjustment",
      "body": "A jump rope that is the correct length is much easier to use than one that is too long or too short. The traditional sizing method: stand on the center of the rope and pull the handles up — the handles should reach armpit height. Most quality ropes are sold adjustable, letting you trim the cable (for steel ropes) or thread it through handles (for PVC ropes) to your ideal length. The correct length actually varies slightly by skill level — beginners often benefit from slightly longer ropes that are easier to time, while advanced athletes doing double-unders prefer shorter ropes with minimal arc. For double-under training specifically, many experienced athletes use cables 1-1.5 feet shorter than the traditional armpit measurement to generate faster, tighter arcs."
    },
    {
      "title": "Handle Design and Grip Comfort",
      "body": "Handle design affects your control and fatigue during extended sessions. Longer handles give more leverage and are preferred for freestyle jump rope tricks. Shorter, lighter handles favor speed and are standard in competition and CrossFit. Handle material matters: bare aluminum is durable and grippy when dry but slippery when sweaty, while foam, rubber, or silicone grips maintain hold through wet conditions. Ball bearings inside the handle allow the cable to rotate independently of the handle — this is critical for smooth, fast jumping because it lets the cable spin freely while your hands stay still. Poor or worn bearings create drag and inconsistent rotation. In quality ropes, the bearings should be sealed and rated for hundreds of thousands of rotations."
    },
    {
      "title": "Learning Double-Unders",
      "body": "Double-unders (passing the rope twice under your feet per jump) are a high-skill movement that dramatically increases jump rope intensity. The technique requires higher jumps, faster wrist rotation, and good timing — most people take several weeks of practice before consistently achieving even 10 consecutive double-unders. For learning: start with a speed rope in your correct length, practice single-unders at high cadence to develop wrist speed, then add occasional double rotations (triple-singles with one double inserted). Common errors include jumping too high, using arm rotation instead of wrist rotation, and using too long a rope. Once you can do 10+ consecutive double-unders, performance improves rapidly. Investing in a quality speed rope significantly eases the learning process."
    },
    {
      "title": "Jump Rope Surfaces and Portability",
      "body": "Jump ropes are among the most portable fitness tools available, weighing under 0.5 lb and fitting in any bag or pocket. However, surface matters for both performance and equipment longevity. Smooth wood floors (like in a gym), rubber flooring, or flat turf are ideal surfaces — they provide consistent bounce and protect the cable. Concrete and asphalt dramatically shorten cable life, especially for thin steel cables. If you regularly train outdoors on hard surfaces, use a thicker PVC-coated rope or replace the cable frequently. Many indoor facilities have jump rope mats (small rubber squares) for protection. Avoid jumping on carpet, which catches the cable's arc — even short carpet significantly disrupts rhythm and increases missed jumps."
    }
  ],
  "faq": [
    {
      "q": "How long should I jump rope each workout?",
      "a": "Jump rope duration depends on your fitness level and workout goals. Beginners should start with 5-10 minute sessions, resting when needed, and build up over several weeks. Intermediate exercisers typically use 15-20 minute sessions as a cardio warm-up or as part of a HIIT circuit. Advanced athletes in boxing and CrossFit contexts may jump rope for 30-45 minutes total across multiple rounds. For calorie burn comparison, jumping rope at moderate intensity burns approximately 10-15 calories per minute — comparable to running at a brisk pace. If you're using jump rope as your primary cardio tool, 20-30 minutes of continuous jumping (with brief rest intervals) provides substantial cardiovascular benefit. Start shorter than you think you need, as jump rope is more fatiguing than it appears, particularly for the calves and ankles."
    },
    {
      "q": "What is the best jump rope for beginners?",
      "a": "Beginners should choose a PVC or PVC-coated rope with adjustable length and comfortable foam handles — the DEGOL Skipping Rope with Counter is an excellent starting point. Key features for beginners: slightly heavier cable (easier to time than ultra-thin speed ropes), handles with a comfortable grip that won't slip during moderate intensity, easy length adjustment, and a cable that won't sting badly on the frequent missed reps that happen early in learning. Speed ropes with 1.5mm steel cables are not recommended for complete beginners — the thin cable moves unpredictably until you develop solid timing, and the cable contact on misses is painful. Start with a basic rope, develop your rhythm and timing, then upgrade to a speed rope once you can jump consistently for 2+ minutes without trips."
    },
    {
      "q": "Can jump rope replace running for cardio?",
      "a": "Yes — jump rope provides comparable or superior cardiovascular conditioning to running at equivalent intensity levels, with some practical advantages. Jump rope burns roughly 10-16 calories per minute, similar to running at a 7-8 minute mile pace, while also developing coordination, timing, and calf strength that running doesn't emphasize. Jump rope is lower impact than running on hard surfaces (though it does load the calves and ankles significantly), and it requires almost no space or equipment. The main limitation compared to running is that jump rope sessions typically max out around 30-45 minutes before fatigue — long-distance endurance training still favors running. For general cardiovascular fitness, weight management, and athletic conditioning, 20-30 minutes of jump rope 3-5 times per week is as effective as equivalent running sessions and adds skill development."
    },
    {
      "q": "How do I stop tripping when jumping rope?",
      "a": "Tripping when jumping rope is almost always caused by one of four issues: incorrect rope length, jumping too high, poor wrist mechanics, or inconsistent rhythm. For length: the rope should reach armpit height when you stand on its center — too long creates excess arc and catches your feet. For jumping height: most people jump far too high, especially early on. You only need 1-2 inches of clearance — think of it as barely leaving the ground rather than jumping. For wrist mechanics: the rotation should come from the wrists, not the arms — your elbows should stay near your sides with small wrist circles driving the rope. For rhythm: count out loud to establish a steady beat. Start slowly and build speed only after you can maintain 30 seconds without trips. As your technique improves, trips will become rare rather than constant."
    },
    {
      "q": "What is the difference between a speed rope and a regular jump rope?",
      "a": "Speed ropes are engineered specifically for fast rotation and performance use, while standard jump ropes prioritize durability and general use. The key differences: cable thickness (speed ropes use 1.5-2mm steel cables; standard ropes use 4-8mm PVC), bearing quality (speed ropes have precision ball bearings allowing up to 300+ RPM rotation; standard ropes have basic swivel connections), handle length (speed ropes have shorter handles for less arm movement), and weight distribution (speed ropes are lighter overall). For casual fitness use or beginners, a standard rope's extra durability and more forgiving cable are advantages. For CrossFit, boxing conditioning, or double-under training, a speed rope's technical advantages make a significant difference in performance. Once you can jump consistently for 1-2 minutes, the upgrade to a speed rope is immediately noticeable in how much smoother and faster the rotation feels."
    }
  ],
  "related_articles": [
    {
      "slug": "best-adjustable-dumbbells-2026",
      "title": "Best Adjustable Dumbbells of 2026: Top Home Gym Picks"
    },
    {
      "slug": "best-cold-plunge-ice-baths-2026",
      "title": "Best Cold Plunge Ice Baths 2026"
    },
    {
      "slug": "best-creatine-supplements-2026",
      "title": "Best Creatine Supplements of 2026: Science-Backed Picks"
    }
  ]
}
